[
 {
  "prof": "Dr. Griffith",
  "at": 1777741208340,
  "id": "xmr81e9zoep8zp",
  "byId": "seed-JordanReyes",
  "code": "BIOL 252",
  "by": "Jordan Reyes",
  "take": "Hard, but the anatomy unit carries straight into the DAT. Go to office hours early.",
  "up": 1783474712729,
  "rating": 5,
  "kind": "prof"
 },
 {
  "at": 1781370008340,
  "id": "xmr81e9zogmq8q",
  "prof": "Dr. Payne",
  "take": "Statistics you’ll actually reuse on research apps. Take it before junior year.",
  "up": 1783474712729,
  "rating": 5,
  "kind": "prof",
  "byId": "seed-NiaThompson",
  "code": "PSYC 210",
  "by": "Nia Thompson"
 },
 {
  "at": 1778864408340,
  "id": "xmr81e9zoi8ea4",
  "prof": "Dr. Griffith",
  "up": 1783474712729,
  "rating": 4,
  "take": "Heavy memorization — draw everything twice and you’re fine.",
  "kind": "prof",
  "byId": "seed-SofiaMarin",
  "by": "Sofia Marin",
  "code": "BIOL 252"
 },
 {
  "up": 1783474712729,
  "rating": 4,
  "take": "Mechanisms over memorizing. His practice sets are basically the exam.",
  "kind": "prof",
  "byId": "seed-ChrisOkafor",
  "by": "Chris Okafor",
  "code": "CHEM 261",
  "at": 1779210008340,
  "id": "xmr81e9zoimi6f",
  "prof": "Dr. Austell"
 },
 {
  "id": "xmr81e9zomf7fe",
  "at": 1780678808340,
  "prof": "Dr. Ramesh",
  "kind": "prof",
  "rating": 3,
  "up": 1783474712729,
  "take": "Fair grader, dry lectures. The reading quizzes sneak up on you.",
  "by": "Maya Feldman",
  "code": "BIOL 205",
  "byId": "seed-MayaFeldman"
 },
 {
  "at": 1780285969932,
  "id": "xmr8opn9o1ie69",
  "prof": null,
  "up": 1783643283328,
  "rating": 5,
  "take": "Brutal weeks 4–8, then everything clicks. Worth it.",
  "kind": "class",
  "byId": "seed-NiaThompson",
  "by": "Nia Thompson",
  "code": "BIOL 252"
 },
 {
  "prof": "Dr. Payne",
  "id": "xmr8opn9o75ohe",
  "at": 1781409169932,
  "code": "PSYC 210",
  "by": "Nia Thompson",
  "byId": "seed-NiaThompson",
  "kind": "prof",
  "take": "Statistics you’ll actually reuse on research apps. Take it before junior year.",
  "up": 1783643283328,
  "rating": 5
 },
 {
  "byId": "seed-MayaFeldman",
  "code": "BIOL 205",
  "by": "Maya Feldman",
  "take": "Fair grader, dry lectures. The reading quizzes sneak up on you.",
  "up": 1783643283328,
  "rating": 3,
  "kind": "prof",
  "prof": "Dr. Ramesh",
  "at": 1780717969932,
  "id": "xmr8opn9o7rdzi"
 },
 {
  "prof": "Dr. Hogan",
  "id": "xmr8opn9od0ere",
  "at": 1779508369932,
  "code": "BIOL 252",
  "by": "Maya Feldman",
  "byId": "seed-MayaFeldman",
  "kind": "prof",
  "take": "Knows the material cold, but the lectures move fast — record them.",
  "up": 1783643283328,
  "rating": 3
 },
 {
  "prof": null,
  "at": 1779767569932,
  "id": "xmr8opn9okd97v",
  "byId": "seed-ChrisOkafor",
  "code": "CHEM 261",
  "by": "Chris Okafor",
  "take": "Orgo is a rite of passage — this version of it is a fair one.",
  "rating": 4,
  "up": 1783643283328,
  "kind": "class"
 },
 {
  "prof": null,
  "at": 1778125969932,
  "id": "xmr8opn9olsk7s",
  "byId": "seed-JordanReyes",
  "code": "BIOL 252",
  "by": "Jordan Reyes",
  "take": "The single most useful course before the DAT, whoever you get.",
  "rating": 4,
  "up": 1783643283328,
  "kind": "class"
 },
 {
  "at": 1778903569932,
  "id": "xmr8opn9oncfsw",
  "prof": "Dr. Griffith",
  "rating": 4,
  "up": 1783643283328,
  "take": "Heavy memorization — draw everything twice and you’re fine.",
  "kind": "prof",
  "byId": "seed-SofiaMarin",
  "by": "Sofia Marin",
  "code": "BIOL 252"
 },
 {
  "id": "xmr8opn9opg9db",
  "at": 1779249169932,
  "prof": "Dr. Austell",
  "kind": "prof",
  "up": 1783643283328,
  "rating": 4,
  "take": "Mechanisms over memorizing. His practice sets are basically the exam.",
  "by": "Chris Okafor",
  "code": "CHEM 261",
  "byId": "seed-ChrisOkafor"
 },
 {
  "prof": "Dr. Griffith",
  "id": "xmr8opn9ovafbo",
  "at": 1777780369932,
  "code": "BIOL 252",
  "by": "Jordan Reyes",
  "byId": "seed-JordanReyes",
  "kind": "prof",
  "take": "Hard, but the anatomy unit carries straight into the DAT. Go to office hours early.",
  "rating": 5,
  "up": 1783643283328
 },
 {
  "by": "Jordan Reyes",
  "code": "BIOL 252",
  "byId": "seed-JordanReyes",
  "kind": "prof",
  "up": 1783691603339,
  "rating": 5,
  "take": "Hard, but the anatomy unit carries straight into the DAT. Go to office hours early.",
  "prof": "Dr. Griffith",
  "id": "xmr9hxomu5m23n",
  "at": 1777829453814
 },
 {
  "byId": "seed-NiaThompson",
  "by": "Nia Thompson",
  "code": "PSYC 210",
  "rating": 5,
  "up": 1783691603339,
  "take": "Statistics you’ll actually reuse on research apps. Take it before junior year.",
  "kind": "prof",
  "prof": "Dr. Payne",
  "at": 1781458253814,
  "id": "xmr9hxomub2o9n"
 },
 {
  "kind": "class",
  "take": "The single most useful course before the DAT, whoever you get.",
  "rating": 4,
  "up": 1783691603339,
  "code": "BIOL 252",
  "by": "Jordan Reyes",
  "byId": "seed-JordanReyes",
  "id": "xmr9hxomucw7i8",
  "at": 1778175053814,
  "prof": null
 },
 {
  "byId": "seed-ChrisOkafor",
  "by": "Chris Okafor",
  "code": "CHEM 261",
  "up": 1783691603339,
  "rating": 4,
  "take": "Mechanisms over memorizing. His practice sets are basically the exam.",
  "kind": "prof",
  "prof": "Dr. Austell",
  "at": 1779298253814,
  "id": "xmr9hxomufiu8j"
 },
 {
  "prof": "Dr. Ramesh",
  "at": 1780767053814,
  "id": "xmr9hxomug9cji",
  "byId": "seed-MayaFeldman",
  "by": "Maya Feldman",
  "code": "BIOL 205",
  "rating": 3,
  "up": 1783691603339,
  "take": "Fair grader, dry lectures. The reading quizzes sneak up on you.",
  "kind": "prof"
 },
 {
  "up": 1783691603339,
  "rating": 3,
  "take": "Knows the material cold, but the lectures move fast — record them.",
  "kind": "prof",
  "byId": "seed-MayaFeldman",
  "by": "Maya Feldman",
  "code": "BIOL 252",
  "at": 1779557453814,
  "id": "xmr9hxomuhuh5x",
  "prof": "Dr. Hogan"
 },
 {
  "by": "Chris Okafor",
  "code": "CHEM 261",
  "byId": "seed-ChrisOkafor",
  "kind": "class",
  "up": 1783691603339,
  "rating": 4,
  "take": "Orgo is a rite of passage — this version of it is a fair one.",
  "prof": null,
  "id": "xmr9hxomul0ide",
  "at": 1779816653814
 },
 {
  "by": "Nia Thompson",
  "code": "BIOL 252",
  "byId": "seed-NiaThompson",
  "kind": "class",
  "up": 1783691603339,
  "rating": 5,
  "take": "Brutal weeks 4–8, then everything clicks. Worth it.",
  "prof": null,
  "id": "xmr9hxomumcf4z",
  "at": 1780335053814
 },
 {
  "take": "Heavy memorization — draw everything twice and you’re fine.",
  "rating": 4,
  "up": 1783691603339,
  "kind": "prof",
  "byId": "seed-SofiaMarin",
  "code": "BIOL 252",
  "by": "Sofia Marin",
  "at": 1778952653814,
  "id": "xmr9hxomuombx3",
  "prof": "Dr. Griffith"
 }
]